GPSminCir.py
GPSminCir-1.0.5.dist-info/LICENSE.txt
GPSminCir-1.0.5.dist-info/METADATA
GPSminCir-1.0.5.dist-info/WHEEL
GPSminCir-1.0.5.dist-info/top_level.txt
GPSminCir-1.0.5.dist-info/RECORD
